nuvla_cli/__init__.py
nuvla_cli/__main__.py
nuvla_cli/common/__init__.py
nuvla_cli/common/cli_builder.py
nuvla_cli/common/common.py
nuvla_cli/common/constants.py
nuvla_cli/common/geo_location.py
nuvla_cli/entity_action_cmd/__init__.py
nuvla_cli/entity_action_cmd/edge.py
nuvla_cli/entity_action_cmd/fleet.py
nuvla_cli/entity_action_cmd/user.py
nuvla_cli/nuvlaio/__init__.py
nuvla_cli/nuvlaio/cli_api.py
nuvla_cli/nuvlaio/device/__init__.py
nuvla_cli/nuvlaio/device/device.py
nuvla_cli/nuvlaio/device/dummy.py
nuvla_cli/nuvlaio/device/local.py
nuvla_cli/nuvlaio/device/release_control.py
nuvla_cli/nuvlaio/device/remote.py
nuvla_cli/nuvlaio/edge.py
nuvla_cli/nuvlaio/nuvlaedge_engine.py
nuvla_cli/nuvlaio/nuvlaio_cli.py
nuvla_cli/schemas/__init__.py
nuvla_cli/schemas/edge_schema.py
nuvla_cli/schemas/engine_schema.py
nuvla_cli/schemas/nuvla_schema.py
nuvla_cli/schemas/user_schema.py
nuvla_cli-1.0.3.dist-info/LICENSE
nuvla_cli-1.0.3.dist-info/WHEEL
nuvla_cli-1.0.3.dist-info/entry_points.txt
nuvla_cli-1.0.3.dist-info/METADATA
nuvla_cli-1.0.3.dist-info/RECORD
