Metadata-Version: 2.1
Name: nuvla-cli
Version: 1.0.3
Summary: CLI tool for local management of Nuvla and NuvlaEdges via terminal
Home-page: https://github.com/nuvla/cli
License: Apache-2.0
Author: Nacho
Author-email: nacho@sixsq.com
Requires-Python: >=3.10,<4.0
Classifier: License :: OSI Approved :: Apache Software License
Classifier: Programming Language :: Python :: 3
Classifier: Programming Language :: Python :: 3.10
Classifier: Programming Language :: Python :: 3.11
Requires-Dist: Shapely (>=1.8.4,<2.0.0)
Requires-Dist: decorator (>=5.1.1,<6.0.0)
Requires-Dist: docker (>=6.0.0,<7.0.0)
Requires-Dist: fabric (>=3.0.1,<4.0.0)
Requires-Dist: nuvla-api (>=3.0.8,<4.0.0)
Requires-Dist: pydantic (>=1.10.0,<2.0.0)
Requires-Dist: pyshp (>=2.3.1,<3.0.0)
Requires-Dist: rich (>=13.0.1,<14.0.0)
Requires-Dist: toml (>=0.10.2,<0.11.0)
Requires-Dist: typer (>=0.9.0,<0.10.0)
Project-URL: Repository, https://github.com/nuvla/cli
